nonebot_plugin_stable_diffusion/__init__.py
nonebot_plugin_stable_diffusion/config.py
nonebot_plugin_stable_diffusion/limiter.py
nonebot_plugin_stable_diffusion-0.0.13.dist-info/LICENSE
nonebot_plugin_stable_diffusion-0.0.13.dist-info/METADATA
nonebot_plugin_stable_diffusion-0.0.13.dist-info/WHEEL
nonebot_plugin_stable_diffusion-0.0.13.dist-info/top_level.txt
nonebot_plugin_stable_diffusion-0.0.13.dist-info/RECORD
