Metadata-Version: 2.1
Name: nonebot-plugin-stable-diffusion
Version: 0.0.13
Summary: nonebot_plugin_stable_diffusion
Home-page: https://github.com/Matrix-King-Studio/nonebot_plugin_stable_diffusion
Author: alex
Author-email: liu_zhao_feng_alex@163.com
Project-URL: Bug Tracker, https://github.com/Matrix-King-Studio/nonebot_plugin_stable_diffusion/issues
Platform: any
Classifier: Programming Language :: Python :: 3
Classifier: License :: OSI Approved :: MIT License
Classifier: Operating System :: OS Independent
Requires-Python: >=3.9
License-File: LICENSE
Requires-Dist: nonebot2 (>=2.0.0-beta.2)
Requires-Dist: nonebot-adapter-onebot
Requires-Dist: httpx (>=0.23.0)
